redreactor/__init__.py
redreactor/__main__.py
redreactor/components/commander/__init__.py
redreactor/components/commander/commander.py
redreactor/components/homeassistant/__init__.py
redreactor/components/homeassistant/binary_sensor.py
redreactor/components/homeassistant/button.py
redreactor/components/homeassistant/common.py
redreactor/components/homeassistant/homeassistant.py
redreactor/components/homeassistant/number.py
redreactor/components/homeassistant/sensor.py
redreactor/components/monitor/__init__.py
redreactor/components/monitor/data.py
redreactor/components/monitor/monitor.py
redreactor/components/mqtt/__init__.py
redreactor/components/mqtt/mqtt.py
redreactor/configuration.py
redreactor/const.py
redreactor/helpers/__init__.py
redreactor/helpers/emitter.py
redreactor/helpers/repeater.py
redreactor/helpers/utils.py
redreactor-0.1.3.dist-info/LICENSE
redreactor-0.1.3.dist-info/METADATA
redreactor-0.1.3.dist-info/WHEEL
redreactor-0.1.3.dist-info/RECORD
