Metadata-Version: 2.1
Name: redreactor
Version: 0.1.3
Summary: Red Reactor Battery Monitoring service with MQTT, and Home Assistant support
Home-page: https://github.com/mreditor97/redreactor
License: MIT
Author: MrEditor97
Author-email: dev@mreditor97.co.uk
Requires-Python: >=3.10,<4.0
Classifier: License :: OSI Approved :: MIT License
Classifier: Programming Language :: Python :: 3
Classifier: Programming Language :: Python :: 3.10
Classifier: Programming Language :: Python :: 3.11
Requires-Dist: paho-mqtt (>=1.6.1,<2.0.0)
Requires-Dist: pi-ina219 (>=1.4.1,<2.0.0)
Requires-Dist: pyyaml (>=6.0,<7.0)
Project-URL: Bug Tracker, https://github.com/mreditor97/redreactor/issues
Project-URL: Changelog, https://github.com/mreditor97/redreactor/releases
Project-URL: Documentation, https://github.com/mreditor97/redreactor
Project-URL: Repository, https://github.com/mreditor97/redreactor
